README.md
setup.py
blinkytools/__init__.py
blinkytools/__main__.py
blinkytools/file_preview.py
blinkytools/gui.py
blinkytools/gui_utils.py
blinkytools/io.py
blinkytools/non_linearity.py
blinkytools/processors.py
blinkytools/utils.py
blinkytools/version.py
blinkytools/video.py
blinkytools/viewer.py
blinkytools.egg-info/PKG-INFO
blinkytools.egg-info/SOURCES.txt
blinkytools.egg-info/dependency_links.txt
blinkytools.egg-info/requires.txt
blinkytools.egg-info/top_level.txt